helix_catalog_sdk/__init__.py
helix_catalog_sdk/catalog.py
helix_catalog_sdk/data_source.py
helix_catalog_sdk/enums.py
helix_catalog_sdk/py.typed
helix_catalog_sdk/repo.py
tests/__init__.py
tests/test_catalog.py
helix.catalog_sdk-0.3.7.dist-info/LICENSE
helix.catalog_sdk-0.3.7.dist-info/METADATA
helix.catalog_sdk-0.3.7.dist-info/WHEEL
helix.catalog_sdk-0.3.7.dist-info/top_level.txt
helix.catalog_sdk-0.3.7.dist-info/RECORD
