Metadata-Version: 2.1
Name: helix.catalog-sdk
Version: 0.3.7
Summary: SDK for interacting with the Helix Data and Connection Catalog
Home-page: https://github.com/icanbwell/helix.catalog-sdk
Author: Michael Vidal
Author-email: michael.vidal@icanbwell.com
License: UNKNOWN
Platform: UNKNOWN
Classifier: Development Status :: 4 - Beta
Classifier: Programming Language :: Python :: 3
Classifier: License :: OSI Approved :: Apache Software License
Classifier: Operating System :: OS Independent
Requires-Python: >=3.7
License-File: LICENSE
Requires-Dist: pygithub (>=1.55)
Requires-Dist: boto3 (>=1.17.110)
Requires-Dist: boto3-stubs (>=1.17.110)
Requires-Dist: chardet (>=4.0.0)
